kyaah/__init__.py
kyaah/api.py
kyaah/base.py
kyaah/server.py
kyaah/utils.py
kyaah/vault.py
kyaah/cli/__init__.py
kyaah-0.1.17.dist-info/LICENSE
kyaah-0.1.17.dist-info/METADATA
kyaah-0.1.17.dist-info/WHEEL
kyaah-0.1.17.dist-info/entry_points.txt
kyaah-0.1.17.dist-info/top_level.txt
kyaah-0.1.17.dist-info/RECORD
