Metadata-Version: 2.1
Name: kyaah
Version: 0.1.17
Summary: Kyaah abstract away cognitive over-head of sending SMTP mail, together with other mailing operations things like, mail with file, tokens etc.
Home-page: https://kyaah.readthedocs.io
Author: Usman Musa
Author-email: usmanmusa1920@gmail.com
License: MIT
Download-URL: https://pypi.org/project/kyaah
Project-URL: Documentation, https://kyaah.readthedocs.io
Project-URL: Source, https://github.com/usmanmusa1920/kyaah
Keywords: kyaah
Platform: any
Classifier: Development Status :: 5 - Production/Stable
Classifier: Environment :: Other Environment
Classifier: Intended Audience :: Developers
Classifier: License :: OSI Approved :: MIT License
Classifier: Natural Language :: English
Classifier: Operating System :: OS Independent
Classifier: Programming Language :: Python
Classifier: Programming Language :: Python :: 3
Classifier: Programming Language :: Python :: 3.7
Classifier: Programming Language :: Python :: 3.8
Classifier: Programming Language :: Python :: 3.9
Classifier: Programming Language :: Python :: 3.10
Classifier: Topic :: Internet
Classifier: Topic :: Communications :: Email
Classifier: Topic :: Software Development :: Libraries :: Python Modules
Requires-Python: >=3.7
License-File: LICENSE
Requires-Dist: aiosmtpd >=1.4.6
Requires-Dist: geocoder >=1.38.1
Requires-Dist: itsdangerous ==0.24
Requires-Dist: rgbpy >=0.0.1
